{"nodes": [{"id": "authviewmodel", "label": "AuthViewModel.cs", "file_type": "code", "source_file": "AclsTracker\\ViewModels\\AuthViewModel.cs", "source_location": "L1"}, {"id": "authviewmodel_authviewmodel", "label": "AuthViewModel", "file_type": "code", "source_file": "AclsTracker\\ViewModels\\AuthViewModel.cs", "source_location": "L17"}, {"id": "observableobject", "label": "ObservableObject", "file_type": "code", "source_file": "", "source_location": ""}, {"id": "authviewmodel_authviewmodel_updateauthstate", "label": ".UpdateAuthState()", "file_type": "code", "source_file": "AclsTracker\\ViewModels\\AuthViewModel.cs", "source_location": "L107"}, {"id": "authviewmodel_authviewmodel_onauthstatechanged", "label": ".OnAuthStateChanged()", "file_type": "code", "source_file": "AclsTracker\\ViewModels\\AuthViewModel.cs", "source_location": "L127"}, {"id": "authviewmodel_authviewmodel_signinwithemailasync", "label": ".SignInWithEmailAsync()", "file_type": "code", "source_file": "AclsTracker\\ViewModels\\AuthViewModel.cs", "source_location": "L152"}, {"id": "authviewmodel_authviewmodel_signupasync", "label": ".SignUpAsync()", "file_type": "code", "source_file": "AclsTracker\\ViewModels\\AuthViewModel.cs", "source_location": "L195"}, {"id": "authviewmodel_authviewmodel_resetpasswordasync", "label": ".ResetPasswordAsync()", "file_type": "code", "source_file": "AclsTracker\\ViewModels\\AuthViewModel.cs", "source_location": "L278"}, {"id": "authviewmodel_authviewmodel_signinwithgoogleasync", "label": ".SignInWithGoogleAsync()", "file_type": "code", "source_file": "AclsTracker\\ViewModels\\AuthViewModel.cs", "source_location": "L315"}, {"id": "authviewmodel_authviewmodel_signinwithappleasync", "label": ".SignInWithAppleAsync()", "file_type": "code", "source_file": "AclsTracker\\ViewModels\\AuthViewModel.cs", "source_location": "L350"}, {"id": "authviewmodel_authviewmodel_signoutasync", "label": ".SignOutAsync()", "file_type": "code", "source_file": "AclsTracker\\ViewModels\\AuthViewModel.cs", "source_location": "L387"}, {"id": "authviewmodel_authviewmodel_loadprofileasync", "label": ".LoadProfileAsync()", "file_type": "code", "source_file": "AclsTracker\\ViewModels\\AuthViewModel.cs", "source_location": "L434"}, {"id": "authviewmodel_authviewmodel_saveprofileasync", "label": ".SaveProfileAsync()", "file_type": "code", "source_file": "AclsTracker\\ViewModels\\AuthViewModel.cs", "source_location": "L458"}, {"id": "authviewmodel_authviewmodel_uploadavatarasync", "label": ".UploadAvatarAsync()", "file_type": "code", "source_file": "AclsTracker\\ViewModels\\AuthViewModel.cs", "source_location": "L491"}, {"id": "authviewmodel_authviewmodel_navigatetologinasync", "label": ".NavigateToLoginAsync()", "file_type": "code", "source_file": "AclsTracker\\ViewModels\\AuthViewModel.cs", "source_location": "L533"}, {"id": "authviewmodel_authviewmodel_navigatetoregisterasync", "label": ".NavigateToRegisterAsync()", "file_type": "code", "source_file": "AclsTracker\\ViewModels\\AuthViewModel.cs", "source_location": "L539"}, {"id": "authviewmodel_authviewmodel_navigatetoprofileasync", "label": ".NavigateToProfileAsync()", "file_type": "code", "source_file": "AclsTracker\\ViewModels\\AuthViewModel.cs", "source_location": "L545"}, {"id": "authviewmodel_authviewmodel_navigatebackasync", "label": ".NavigateBackAsync()", "file_type": "code", "source_file": "AclsTracker\\ViewModels\\AuthViewModel.cs", "source_location": "L551"}, {"id": "authviewmodel_authviewmodel_clearregisterform", "label": ".ClearRegisterForm()", "file_type": "code", "source_file": "AclsTracker\\ViewModels\\AuthViewModel.cs", "source_location": "L559"}], "edges": [{"source": "authviewmodel", "target": "alerts", "relation": "imports", "confidence": "EXTRACTED", "source_file": "AclsTracker\\ViewModels\\AuthViewModel.cs", "source_location": "L1", "weight": 1.0}, {"source": "authviewmodel", "target": "componentmodel", "relation": "imports", "confidence": "EXTRACTED", "source_file": "AclsTracker\\ViewModels\\AuthViewModel.cs", "source_location": "L2", "weight": 1.0}, {"source": "authviewmodel", "target": "input", "relation": "imports", "confidence": "EXTRACTED", "source_file": "AclsTracker\\ViewModels\\AuthViewModel.cs", "source_location": "L3", "weight": 1.0}, {"source": "authviewmodel", "target": "models", "relation": "imports", "confidence": "EXTRACTED", "source_file": "AclsTracker\\ViewModels\\AuthViewModel.cs", "source_location": "L4", "weight": 1.0}, {"source": "authviewmodel", "target": "auth", "relation": "imports", "confidence": "EXTRACTED", "source_file": "AclsTracker\\ViewModels\\AuthViewModel.cs", "source_location": "L5", "weight": 1.0}, {"source": "authviewmodel", "target": "sync", "relation": "imports", "confidence": "EXTRACTED", "source_file": "AclsTracker\\ViewModels\\AuthViewModel.cs", "source_location": "L6", "weight": 1.0}, {"source": "authviewmodel", "target": "logging", "relation": "imports", "confidence": "EXTRACTED", "source_file": "AclsTracker\\ViewModels\\AuthViewModel.cs", "source_location": "L7", "weight": 1.0}, {"source": "authviewmodel", "target": "exceptions", "relation": "imports", "confidence": "EXTRACTED", "source_file": "AclsTracker\\ViewModels\\AuthViewModel.cs", "source_location": "L8", "weight": 1.0}, {"source": "authviewmodel", "target": "authviewmodel_authviewmodel", "relation": "contains", "confidence": "EXTRACTED", "source_file": "AclsTracker\\ViewModels\\AuthViewModel.cs", "source_location": "L17", "weight": 1.0}, {"source": "authviewmodel_authviewmodel", "target": "observableobject", "relation": "inherits", "confidence": "EXTRACTED", "source_file": "AclsTracker\\ViewModels\\AuthViewModel.cs", "source_location": "L17", "weight": 1.0}, {"source": "authviewmodel_authviewmodel", "target": "authviewmodel_authviewmodel_updateauthstate", "relation": "method", "confidence": "EXTRACTED", "source_file": "AclsTracker\\ViewModels\\AuthViewModel.cs", "source_location": "L107", "weight": 1.0}, {"source": "authviewmodel_authviewmodel", "target": "authviewmodel_authviewmodel_onauthstatechanged", "relation": "method", "confidence": "EXTRACTED", "source_file": "AclsTracker\\ViewModels\\AuthViewModel.cs", "source_location": "L127", "weight": 1.0}, {"source": "authviewmodel_authviewmodel", "target": "authviewmodel_authviewmodel_signinwithemailasync", "relation": "method", "confidence": "EXTRACTED", "source_file": "AclsTracker\\ViewModels\\AuthViewModel.cs", "source_location": "L152", "weight": 1.0}, {"source": "authviewmodel_authviewmodel", "target": "authviewmodel_authviewmodel_signupasync", "relation": "method", "confidence": "EXTRACTED", "source_file": "AclsTracker\\ViewModels\\AuthViewModel.cs", "source_location": "L195", "weight": 1.0}, {"source": "authviewmodel_authviewmodel", "target": "authviewmodel_authviewmodel_resetpasswordasync", "relation": "method", "confidence": "EXTRACTED", "source_file": "AclsTracker\\ViewModels\\AuthViewModel.cs", "source_location": "L278", "weight": 1.0}, {"source": "authviewmodel_authviewmodel", "target": "authviewmodel_authviewmodel_signinwithgoogleasync", "relation": "method", "confidence": "EXTRACTED", "source_file": "AclsTracker\\ViewModels\\AuthViewModel.cs", "source_location": "L315", "weight": 1.0}, {"source": "authviewmodel_authviewmodel", "target": "authviewmodel_authviewmodel_signinwithappleasync", "relation": "method", "confidence": "EXTRACTED", "source_file": "AclsTracker\\ViewModels\\AuthViewModel.cs", "source_location": "L350", "weight": 1.0}, {"source": "authviewmodel_authviewmodel", "target": "authviewmodel_authviewmodel_signoutasync", "relation": "method", "confidence": "EXTRACTED", "source_file": "AclsTracker\\ViewModels\\AuthViewModel.cs", "source_location": "L387", "weight": 1.0}, {"source": "authviewmodel_authviewmodel", "target": "authviewmodel_authviewmodel_loadprofileasync", "relation": "method", "confidence": "EXTRACTED", "source_file": "AclsTracker\\ViewModels\\AuthViewModel.cs", "source_location": "L434", "weight": 1.0}, {"source": "authviewmodel_authviewmodel", "target": "authviewmodel_authviewmodel_saveprofileasync", "relation": "method", "confidence": "EXTRACTED", "source_file": "AclsTracker\\ViewModels\\AuthViewModel.cs", "source_location": "L458", "weight": 1.0}, {"source": "authviewmodel_authviewmodel", "target": "authviewmodel_authviewmodel_uploadavatarasync", "relation": "method", "confidence": "EXTRACTED", "source_file": "AclsTracker\\ViewModels\\AuthViewModel.cs", "source_location": "L491", "weight": 1.0}, {"source": "authviewmodel_authviewmodel", "target": "authviewmodel_authviewmodel_navigatetologinasync", "relation": "method", "confidence": "EXTRACTED", "source_file": "AclsTracker\\ViewModels\\AuthViewModel.cs", "source_location": "L533", "weight": 1.0}, {"source": "authviewmodel_authviewmodel", "target": "authviewmodel_authviewmodel_navigatetoregisterasync", "relation": "method", "confidence": "EXTRACTED", "source_file": "AclsTracker\\ViewModels\\AuthViewModel.cs", "source_location": "L539", "weight": 1.0}, {"source": "authviewmodel_authviewmodel", "target": "authviewmodel_authviewmodel_navigatetoprofileasync", "relation": "method", "confidence": "EXTRACTED", "source_file": "AclsTracker\\ViewModels\\AuthViewModel.cs", "source_location": "L545", "weight": 1.0}, {"source": "authviewmodel_authviewmodel", "target": "authviewmodel_authviewmodel_navigatebackasync", "relation": "method", "confidence": "EXTRACTED", "source_file": "AclsTracker\\ViewModels\\AuthViewModel.cs", "source_location": "L551", "weight": 1.0}, {"source": "authviewmodel_authviewmodel", "target": "authviewmodel_authviewmodel_clearregisterform", "relation": "method", "confidence": "EXTRACTED", "source_file": "AclsTracker\\ViewModels\\AuthViewModel.cs", "source_location": "L559", "weight": 1.0}, {"source": "authviewmodel_authviewmodel_signupasync", "target": "authviewmodel_authviewmodel_clearregisterform", "relation": "calls", "confidence": "EXTRACTED", "source_file": "AclsTracker\\ViewModels\\AuthViewModel.cs", "source_location": "L237", "weight": 1.0}]}